science_jubilee/Machine.py
science_jubilee/__init__.py
science_jubilee/calibration/BasicGelPrinting.ipynb
science_jubilee/calibration/CalibrationControlPanel.py
science_jubilee/calibration/GelPrintingTests.ipynb
science_jubilee/calibration/IntegrationTests.ipynb
science_jubilee/calibration/LabAutomationDeckCalibration.ipynb
science_jubilee/calibration/SetToolParkingPositions.ipynb
science_jubilee/calibration/SyringeExtruder-Test.ipynb
science_jubilee/calibration/ToolAlignmentXY.ipynb
science_jubilee/calibration/templates/lab_automation_deck_template.json
science_jubilee/calibration/templates/tfree.g
science_jubilee/calibration/templates/tpost.g
science_jubilee/calibration/templates/tpre.g
science_jubilee/decks/Deck.py
science_jubilee/decks/LabAutomation_Wellplate_Reference_Coordinate_System.md
science_jubilee/decks/Plate.py
science_jubilee/decks/__init__.py
science_jubilee/decks/deck_definition/lab_automation_deck.json
science_jubilee/decks/deck_definition/lab_automation_deck_MA.json
science_jubilee/decks/deck_definition/lab_automation_deck_MAfeb.json
science_jubilee/decks/deck_definition/lab_automation_deck_blair.json
science_jubilee/labware/Labware.py
science_jubilee/labware/__init__.py
science_jubilee/labware/labware_definition/20mlscintillation_12_wellplate_18000ul.json
science_jubilee/labware/labware_definition/agilent_1_reservoir_290ml.json
science_jubilee/labware/labware_definition/corning_96_wellplate_360ul_flat.json
science_jubilee/labware/labware_definition/falcon_48_wellplate_1500ul.json
science_jubilee/labware/labware_definition/fisherbrand_96_wellplate_360ul.json
science_jubilee/labware/labware_definition/generic_petri_dish_100ml.json
science_jubilee/labware/labware_definition/greiner_24_wellplate_3300ul.json
science_jubilee/labware/labware_definition/opentrons_96_tiprack_300ul.json
science_jubilee/labware/labware_definition/scienfocus_6_wellplate_15900ul.json
science_jubilee/tools/Camera.py
science_jubilee/tools/Loop.py
science_jubilee-0.3.2.dist-info/LICENSE.txt
science_jubilee-0.3.2.dist-info/METADATA
science_jubilee-0.3.2.dist-info/WHEEL
science_jubilee-0.3.2.dist-info/top_level.txt
science_jubilee-0.3.2.dist-info/RECORD
