Metadata-Version: 2.1
Name: science-jubilee
Version: 0.3.2
Summary: Make science with Jubilee
Home-page: https://github.com/machineagency/science-jubilee
Author: Machine Agency, Pozzo Research Group
Author-email: b1air@uw.edu, politim@uw.edu, bgpelkie@uw.edu
License: MIT
Project-URL: Documentation, https://science-jubilee.readthedocs.io/
Project-URL: Source, https://github.com/machineagency/science-jubilee
Project-URL: Tracker, https://github.com/machineagency/science-jubilee/issues
Project-URL: Twitter, https://twitter.com/machine_agency
Keywords: jubilee,science
Platform: any
Classifier: Development Status :: 4 - Beta
Classifier: Programming Language :: Python :: 3
Classifier: License :: OSI Approved :: MIT License
Classifier: Operating System :: OS Independent
Requires-Python: >=3.8
License-File: LICENSE.txt
Requires-Dist: pyserial
Requires-Dist: requests
Requires-Dist: ipykernel
Requires-Dist: numpy
Requires-Dist: opencv-contrib-python
Requires-Dist: matplotlib
Requires-Dist: Jinja2
Requires-Dist: sphinx
Requires-Dist: sphinx-design
Requires-Dist: pydata-sphinx-theme
Requires-Dist: sphinx-autoapi
Requires-Dist: adafruit-mcp4725
Requires-Dist: Adafruit-Blinka
Requires-Dist: ipywidgets
Requires-Dist: picamera ; platform_machine == "aarch64"
Provides-Extra: testing
Requires-Dist: setuptools ; extra == 'testing'
Requires-Dist: pytest ; extra == 'testing'
Requires-Dist: pytest-cov ; extra == 'testing'
Requires-Dist: pre-commit ; extra == 'testing'
Requires-Dist: sphinx ; extra == 'testing'
Requires-Dist: tox ; extra == 'testing'
